tronblock/__init__.py
tronblock/version.py
tronblock-0.0.1.dist-info/LICENCE
tronblock-0.0.1.dist-info/METADATA
tronblock-0.0.1.dist-info/WHEEL
tronblock-0.0.1.dist-info/top_level.txt
tronblock-0.0.1.dist-info/RECORD
