Metadata-Version: 2.1
Name: tronblock
Version: 0.0.1
Summary: Tron Block
Home-page: https://github.com/YasenWang/tronblock
Author: Yasen Wang
Author-email: yasen@yasenstudio.com
License: UNKNOWN
Platform: UNKNOWN
Classifier: Programming Language :: Python :: 3
Classifier: License :: OSI Approved :: MIT License
Classifier: Operating System :: OS Independent
License-File: LICENCE
